redmine/__init__.py
redmine/main.py
redmine/tables.py
redmine/utils.py
Redmine_CLI_Tool-1.0.5.dist-info/METADATA
Redmine_CLI_Tool-1.0.5.dist-info/WHEEL
Redmine_CLI_Tool-1.0.5.dist-info/entry_points.txt
Redmine_CLI_Tool-1.0.5.dist-info/top_level.txt
Redmine_CLI_Tool-1.0.5.dist-info/RECORD
